configwebui/__init__.py
configwebui/app.py
configwebui/config.py
configwebui/utils.py
configwebui/static/css/bootstrap.min.css
configwebui/static/css/fontawesome.all.css
configwebui/static/css/index.css
configwebui/static/icon/apple-touch-icon.png
configwebui/static/icon/favicon-96x96.png
configwebui/static/icon/favicon.ico
configwebui/static/icon/favicon.svg
configwebui/static/icon/site.webmanifest
configwebui/static/icon/web-app-manifest-192x192.png
configwebui/static/icon/web-app-manifest-512x512.png
configwebui/static/js/bootstrap.bundle.min.js
configwebui/static/js/index.js
configwebui/static/js/jquery.slim.min.js
configwebui/static/js/jsoneditor.min.js
configwebui/static/webfonts/fa-brands-400.eot
configwebui/static/webfonts/fa-brands-400.svg
configwebui/static/webfonts/fa-brands-400.ttf
configwebui/static/webfonts/fa-brands-400.woff
configwebui/static/webfonts/fa-brands-400.woff2
configwebui/static/webfonts/fa-regular-400.eot
configwebui/static/webfonts/fa-regular-400.svg
configwebui/static/webfonts/fa-regular-400.ttf
configwebui/static/webfonts/fa-regular-400.woff
configwebui/static/webfonts/fa-regular-400.woff2
configwebui/static/webfonts/fa-solid-900.eot
configwebui/static/webfonts/fa-solid-900.svg
configwebui/static/webfonts/fa-solid-900.ttf
configwebui/static/webfonts/fa-solid-900.woff
configwebui/static/webfonts/fa-solid-900.woff2
configwebui/templates/index.html
configwebui_lucien-0.3.0.dist-info/licenses/LICENSE
configwebui_lucien-0.3.0.dist-info/METADATA
configwebui_lucien-0.3.0.dist-info/WHEEL
configwebui_lucien-0.3.0.dist-info/top_level.txt
configwebui_lucien-0.3.0.dist-info/RECORD
