Metadata-Version: 2.4
Name: configwebui-lucien
Version: 0.3.0
Summary: A simple web-based configuration editor for Python applications.
Author-email: Lucien Shaw <myxlc55@outlook.com>
License-Expression: MIT
Project-URL: Homepage, https://github.com/lucienshawls/py-config-web-ui
Project-URL: Documentation, https://github.com/lucienshawls/py-config-web-ui/blob/master/README.md
Project-URL: Release notes, https://github.com/lucienshawls/py-config-web-ui/releases
Project-URL: Source, https://github.com/lucienshawls/py-config-web-ui.git
Project-URL: Tracker, https://github.com/lucienshawls/py-config-web-ui/issues
Keywords: configuration,editor,web,tool,json,yaml,ui,flask
Classifier: Development Status :: 4 - Beta
Classifier: Framework :: Flask
Classifier: Intended Audience :: Developers
Classifier: Natural Language :: English
Classifier: Natural Language :: Chinese (Simplified)
Classifier: Operating System :: OS Independent
Classifier: Programming Language :: JavaScript
Classifier: Programming Language :: Python
Classifier: Programming Language :: Python :: 3
Classifier: Programming Language :: Python :: 3.10
Classifier: Programming Language :: Python :: 3.11
Classifier: Programming Language :: Python :: 3.12
Classifier: Programming Language :: Python :: 3.13
Classifier: Programming Language :: Python :: 3 :: Only
Classifier: Programming Language :: Python :: Implementation :: CPython
Classifier: Topic :: Software Development :: Libraries :: Python Modules
Classifier: Topic :: Software Development :: User Interfaces
Requires-Python: >=3.10
License-File: LICENSE
Requires-Dist: Flask
Requires-Dist: jsonschema
Dynamic: license-file
